archivy_espial/__init__.py
archivy_espial/config.py
archivy_espial/espial.js
archivy_espial-0.1.1.dist-info/METADATA
archivy_espial-0.1.1.dist-info/WHEEL
archivy_espial-0.1.1.dist-info/entry_points.txt
archivy_espial-0.1.1.dist-info/top_level.txt
archivy_espial-0.1.1.dist-info/RECORD
